hydride/names.pickle
hydride/relax.cpython-312-darwin.so
hydride/fragments.pickle
hydride/add.py
hydride/relax.c
hydride/charge.py
hydride/__init__.py
hydride/names.py
hydride/cli.py
hydride/fragments.py
hydride-1.2.3.dist-info/RECORD
hydride-1.2.3.dist-info/WHEEL
hydride-1.2.3.dist-info/entry_points.txt
hydride-1.2.3.dist-info/LICENSE.rst
hydride-1.2.3.dist-info/top_level.txt
hydride-1.2.3.dist-info/METADATA
