Metadata-Version: 2.1
Name: hydride
Version: 1.2.3
Summary: Adding hydrogen atoms to molecular models
Author: The 'Hydride' contributors
License: BSD 3-Clause License
Project-URL: homepage, https://hydride.biotite-python.org
Project-URL: repository, https://github.com/biotite-dev/hydride
Project-URL: documentation, https://hydride.biotite-python.org
Classifier: Development Status :: 5 - Production/Stable
Classifier: Intended Audience :: Developers
Classifier: Intended Audience :: Science/Research
Classifier: License :: OSI Approved :: BSD License
Classifier: Natural Language :: English
Classifier: Operating System :: POSIX :: Linux
Classifier: Operating System :: MacOS
Classifier: Operating System :: Microsoft :: Windows
Classifier: Programming Language :: Python :: 3
Classifier: Programming Language :: Python :: Implementation :: CPython
Classifier: Topic :: Scientific/Engineering :: Bio-Informatics
Requires-Python: >=3.10
License-File: LICENSE.rst
Requires-Dist: biotite>=0.40
Requires-Dist: numpy>=1.25
Provides-Extra: lint
Requires-Dist: ruff==0.5.2; extra == "lint"
Provides-Extra: test
Requires-Dist: pytest; extra == "test"
